README.md
setup.cfg
setup.py
pytree/__init__.py
pytree/data/__init__.py
pytree/data/config.py
pytree/data/constituency_tree.py
pytree/data/data_collator.py
pytree/data/dependency_tree.py
pytree/data/glove_tokenizer.py
pytree/data/packed_tree.py
pytree/data/utils.py
pytree/models/__init__.py
pytree/models/tree_lstm.py
pytree/models/child_sum/__init__.py
pytree/models/child_sum/configuration_child_sum.py
pytree/models/child_sum/modeling_child_sum.py
pytree/models/n_ary/__init__.py
pytree/models/n_ary/configuration_n_ary.py
pytree/models/n_ary/modeling_n_ary.py
pytree/models/similarity/__init__.py
pytree/models/similarity/configuration_similarity.py
pytree/models/similarity/modeling_similarity.py
rvnn.egg-info/PKG-INFO
rvnn.egg-info/SOURCES.txt
rvnn.egg-info/dependency_links.txt
rvnn.egg-info/top_level.txt