Metadata-Version: 2.1
Name: rvnn
Version: 0.0.1
Summary: A PyTorch package for recursive neural networks.
Home-page: https://github.com/AntoineSimoulin/pytree/tree/main
Author: Antoine Simoulin
Author-email: antoine.simoulin@gmail.com
License: UNKNOWN
Download-URL: https://github.com/AntoineSimoulin/pytree/archive/refs/tags/v0.0.1-alpha.tar.gz
Platform: UNKNOWN
Classifier: Programming Language :: Python :: 3
Classifier: License :: OSI Approved :: Apache Software License
Classifier: Operating System :: OS Independent
